.codecov.yml
.flake8
.readthedocs.yml
.travis.yml
AUTHORS.rst
LICENSE
MANIFEST.in
README.rst
setup.cfg
setup.py
tox.ini
data/README.rst
data/gmt_files/README.rst
data/gmt_files/concatenated_merge.gmt
data/gmt_files/kegg_geneset_final.gmt
data/gmt_files/mpath_geneset.gmt
data/gmt_files/msigdb_kegg.gmt
data/gmt_files/msigdb_reactome.gmt
data/gmt_files/reactome_geneset_final.gmt
data/gmt_files/wikipathways_geneset_final.gmt
data/gmt_files/analogs/kegg_reactome_analogs.gmt
data/gmt_files/analogs/mpath_analogs.gmt
data/gmt_files/analogs/reactome_wikipathways_analogs.gmt
data/gmt_files/analogs/wikipathways_kegg_analogs.gmt
data/results/gsea/README.rst
docs/Makefile
docs/source/cli.rst
docs/source/conf.py
docs/source/constants.rst
docs/source/index.rst
docs/source/mappings.rst
docs/source/pipeline.rst
docs/source/enrichment/fcs.rst
docs/source/enrichment/ora.rst
docs/source/enrichment/pt.rst
docs/source/enrichment/utils.rst
docs/source/prediction/binary.rst
docs/source/prediction/multiclass.rst
docs/source/prediction/survival.rst
docs/source/prediction/utils.rst
src/pathway_forte/__init__.py
src/pathway_forte/__main__.py
src/pathway_forte/cli.py
src/pathway_forte/constants.py
src/pathway_forte/export_genesets_to_gmt.py
src/pathway_forte/mappings.py
src/pathway_forte/utils.py
src/pathway_forte.egg-info/PKG-INFO
src/pathway_forte.egg-info/SOURCES.txt
src/pathway_forte.egg-info/dependency_links.txt
src/pathway_forte.egg-info/entry_points.txt
src/pathway_forte.egg-info/not-zip-safe
src/pathway_forte.egg-info/requires.txt
src/pathway_forte.egg-info/top_level.txt
src/pathway_forte/evaluation/__init__.py
src/pathway_forte/evaluation/distribution.py
src/pathway_forte/pathway_enrichment/__init__.py
src/pathway_forte/pathway_enrichment/functional_class.py
src/pathway_forte/pathway_enrichment/over_representation.py
src/pathway_forte/pathway_enrichment/topology.py
src/pathway_forte/pipeline/__init__.py
src/pathway_forte/pipeline/binary.py
src/pathway_forte/pipeline/export.py
src/pathway_forte/pipeline/geometric.py
src/pathway_forte/pipeline/gsea.py
src/pathway_forte/pipeline/gsea_msig.py
src/pathway_forte/pipeline/import_gmt.py
src/pathway_forte/pipeline/ssgsea.py
src/pathway_forte/pipeline/stability.py
src/pathway_forte/pipeline/subtype.py
