Metadata-Version: 1.2
Name: pathway-forte
Version: 0.0.2
Summary: A Python package for comparing the effect of pathway database choice in functional enrichment and classification methods
Home-page: https://github.com/pathwayforte
Author: Daniel Domingo-Fernández
Author-email: danieldomingofernandez@hotmail.com
License: Apache 2.0 License
Download-URL: https://github.com/pathwayforte/pathway-forte
Keywords: Pathway Databases,Systems Biology,Networks Biology,Pathway Enrichment,Machine Learning
Platform: UNKNOWN
Classifier: Development Status :: 4 - Beta
Classifier: Environment :: Console
Classifier: Intended Audience :: Developers
Classifier: Intended Audience :: Science/Research
Classifier: License :: OSI Approved :: Apache Software License
Classifier: Operating System :: OS Independent
Classifier: Programming Language :: Python
Classifier: Programming Language :: Python :: 3.7
Classifier: Programming Language :: Python :: 3.6
Classifier: Programming Language :: Python :: 3 :: Only
Classifier: Topic :: Scientific/Engineering :: Bio-Informatics
Requires-Python: >=3.6
